{"Holy Cross Navy and Old Gold Debate and Speech Exhibition": {"Bellaire DN": {"tournamentComp": 2.0, "fullNames": "Pramit De & Milan Narayan", "lastNames": ["De", "Narayan"], "prelimRecord": [6, 0], "prelimRank": [1, 56], "breakRecord": [2, 1], "eliminated": [1, 2, "Quarterfinals", "Quarterfinals", "University YP"], "speaks": [{"name": "De Pramit", "rawAVG": 29.0, "adjAVG": 29.0}, {"name": "Narayan Milan", "rawAVG": 28.83, "adjAVG": 29.0}], "goldBid": false, "silverBid": false, "breakBoost": 4, "tournamentBoost": 1, "OPwpm": 3.0}, "Bellaire LT": {"tournamentComp": 1.8, "fullNames": "Bryce Liu & Sernry Tu", "lastNames": ["Liu", "Tu"], "prelimRecord": [6, 0], "prelimRank": [2, 56], "breakRecord": [1, 1], "eliminated": [1, 2, "Octafinals", "Octafinals", "University CT"], "speaks": [{"name": "Liu Bryce", "rawAVG": 28.25, "adjAVG": 28.25}, {"name": "Tu Sernry", "rawAVG": 28.5, "adjAVG": 28.5}], "goldBid": false, "silverBid": false, "breakBoost": 3, "tournamentBoost": 1, "OPwpm": 3.6}, "Bellaire RS": {"tournamentComp": 3.4, "fullNames": "Vedanth Ramabhadran & Andrew Sun", "lastNames": ["Ramabhadran", "Sun"], "prelimRecord": [6, 0], "prelimRank": [3, 56], "breakRecord": [4, 1], "eliminated": null, "speaks": [{"name": "Ramabhadran Vedanth", "rawAVG": 29.4, "adjAVG": 29.4}, {"name": "Sun Andrew", "rawAVG": 29.3, "adjAVG": 29.3}], "goldBid": true, "silverBid": false, "breakBoost": 6, "tournamentBoost": 1, "OPwpm": 3.4}, "Bellaire BF": {"tournamentComp": 2.199, "fullNames": "Omar Busaidy & William Fan", "lastNames": ["Busaidy", "Fan"], "prelimRecord": [5, 1], "prelimRank": [4, 56], "breakRecord": [3, 1], "eliminated": [0, 0, "Semis", "Semifinals", "Bellaire RS"], "speaks": [{"name": "Busaidy Omar", "rawAVG": 28.67, "adjAVG": 28.67}, {"name": "Fan William", "rawAVG": 28.75, "adjAVG": 28.75}], "goldBid": false, "silverBid": true, "breakBoost": 5, "tournamentBoost": 1, "OPwpm": 3.167}, "Bellaire HP": {"tournamentComp": 1.458, "fullNames": "Amy He & Kalina Peneva", "lastNames": ["He", "Peneva"], "prelimRecord": [5, 1], "prelimRank": [5, 56], "breakRecord": [1, 1], "eliminated": [0, 3, "Octafinals", "Octafinals", "Altamont SG"], "speaks": [{"name": "He Amy", "rawAVG": 28.75, "adjAVG": 28.88}, {"name": "Peneva Kalina", "rawAVG": 28.75, "adjAVG": 28.75}], "goldBid": false, "silverBid": false, "breakBoost": 3, "tournamentBoost": 1, "OPwpm": 3.5}, "Ransom Everglades KG": {"tournamentComp": 2.129, "fullNames": "Dina Kaplan & Cecilia Granda-Scott", "lastNames": ["Kaplan", "Granda-Scott"], "prelimRecord": [5, 1], "prelimRank": [6, 56], "breakRecord": [2, 1], "eliminated": [1, 2, "Quarterfinals", "Quarterfinals", "University CT"], "speaks": [{"name": "Kaplan Dina", "rawAVG": 28.17, "adjAVG": 28.6}, {"name": "Granda-Scott Cecilia", "rawAVG": 28.33, "adjAVG": 28.33}], "goldBid": false, "silverBid": false, "breakBoost": 4, "tournamentBoost": 1, "OPwpm": 3.833}, "Bergen County Academies CK": {"tournamentComp": 0.741, "fullNames": "Andrew Chun & Neil Kreibich", "lastNames": ["Chun", "Kreibich"], "prelimRecord": [4, 2], "prelimRank": [7, 56], "breakRecord": [0, 1], "eliminated": [1, 2, "Double Octafinals", "Double Octafinals", "BergenTech KG"], "speaks": [{"name": "Chun Andrew", "rawAVG": 28.75, "adjAVG": 28.75}, {"name": "Kreibich Neil", "rawAVG": 28.33, "adjAVG": 28.33}], "goldBid": false, "silverBid": false, "breakBoost": 2, "tournamentBoost": 1, "OPwpm": 3.333}, "Bergen County Academies DS": {"tournamentComp": 1.167, "fullNames": "Rachel Disler & Lea Smolyanskiy", "lastNames": ["Disler", "Smolyanskiy"], "prelimRecord": [4, 2], "prelimRank": [8, 56], "breakRecord": [1, 1], "eliminated": [0, 3, "Octafinals", "Octafinals", "Bellaire BF"], "speaks": [{"name": "Disler Rachel", "rawAVG": 28.67, "adjAVG": 28.67}, {"name": "Smolyanskiy Lea", "rawAVG": 28.67, "adjAVG": 28.62}], "goldBid": false, "silverBid": false, "breakBoost": 3, "tournamentBoost": 1, "OPwpm": 3.5}, "BergenTech KG": {"tournamentComp": 1.278, "fullNames": "Akil Kasubhai & Samuel Grinberg", "lastNames": ["Kasubhai", "Grinberg"], "prelimRecord": [4, 2], "prelimRank": [9, 56], "breakRecord": [1, 1], "eliminated": [1, 2, "Octafinals", "Octafinals", "Bellaire DN"], "speaks": [{"name": "Kasubhai Akil", "rawAVG": 28.25, "adjAVG": 28.25}, {"name": "Grinberg Samuel", "rawAVG": 28.58, "adjAVG": 28.58}], "goldBid": false, "silverBid": false, "breakBoost": 3, "tournamentBoost": 1, "OPwpm": 3.833}, "Durham ZW": {"tournamentComp": 1.333, "fullNames": "Brian Zhou & Paul Wang", "lastNames": ["Zhou", "Wang"], "prelimRecord": [4, 2], "prelimRank": [10, 56], "breakRecord": [1, 1], "eliminated": [0, 3, "Octafinals", "Octafinals", "Ransom Everglades KG"], "speaks": [{"name": "Zhou Brian", "rawAVG": 29.0, "adjAVG": 28.75}, {"name": "Wang Paul", "rawAVG": 28.7, "adjAVG": 28.7}], "goldBid": false, "silverBid": false, "breakBoost": 3, "tournamentBoost": 1, "OPwpm": 4.0}, "Livingston ZS": {"tournamentComp": 1.056, "fullNames": "Matthew Zhang & Rahul Shah", "lastNames": ["Zhang", "Shah"], "prelimRecord": [4, 2], "prelimRank": [11, 56], "breakRecord": [1, 1], "eliminated": [1, 2, "Octafinals", "Octafinals", "Bellaire RS"], "speaks": [{"name": "Zhang Matthew", "rawAVG": 28.33, "adjAVG": 28.33}, {"name": "Shah Rahul", "rawAVG": 28.67, "adjAVG": 28.67}], "goldBid": false, "silverBid": false, "breakBoost": 3, "tournamentBoost": 1, "OPwpm": 3.167}, "Ransom Everglades JR": {"tournamentComp": 1.222, "fullNames": "Andre Joseph & Nicole Rodriguez", "lastNames": ["Joseph", "Rodriguez"], "prelimRecord": [4, 2], "prelimRank": [12, 56], "breakRecord": [1, 1], "eliminated": [0, 0, "Octafinals", "Octafinals", "Ransom Everglades TR"], "speaks": [{"name": "Joseph Andre", "rawAVG": 28.75, "adjAVG": 28.75}, {"name": "Rodriguez Nicole", "rawAVG": 29.0, "adjAVG": 29.0}], "goldBid": false, "silverBid": false, "breakBoost": 3, "tournamentBoost": 1, "OPwpm": 3.667}, "Ransom Everglades TR": {"tournamentComp": 1.63, "fullNames": "Eva Tariko & Sophia Rubinstein", "lastNames": ["Tariko", "Rubinstein"], "prelimRecord": [4, 2], "prelimRank": [13, 56], "breakRecord": [1, 2], "eliminated": [1, 2, "Quarterfinals", "Quarterfinals", "Bellaire RS"], "speaks": [{"name": "Tariko Eva", "rawAVG": 29.08, "adjAVG": 29.12}, {"name": "Rubinstein Sophia", "rawAVG": 29.17, "adjAVG": 29.0}], "goldBid": false, "silverBid": false, "breakBoost": 4, "tournamentBoost": 1, "OPwpm": 3.667}, "Altamont SG": {"tournamentComp": 1.852, "fullNames": "Wesley Sudarshan & Pranav Goli", "lastNames": ["Sudarshan", "Goli"], "prelimRecord": [4, 2], "prelimRank": [14, 56], "breakRecord": [2, 1], "eliminated": [0, 3, "Quarterfinals", "Quarterfinals", "Bellaire BF"], "speaks": [{"name": "Sudarshan Wesley", "rawAVG": 28.58, "adjAVG": 28.58}, {"name": "Goli Pranav", "rawAVG": 28.67, "adjAVG": 28.67}], "goldBid": false, "silverBid": false, "breakBoost": 4, "tournamentBoost": 1, "OPwpm": 4.167}, "Bromfield AA": {"tournamentComp": 0.704, "fullNames": "Sophia Atwell & Matthew Atwell", "lastNames": ["Atwell", "Atwell"], "prelimRecord": [4, 2], "prelimRank": [15, 56], "breakRecord": [0, 1], "eliminated": [0, 3, "Double Octafinals", "Double Octafinals", "Livingston ZS"], "speaks": [{"name": "Atwell Sophia", "rawAVG": 28.33, "adjAVG": 28.33}, {"name": "Atwell Matthew", "rawAVG": 28.58, "adjAVG": 28.58}], "goldBid": false, "silverBid": false, "breakBoost": 2, "tournamentBoost": 1, "OPwpm": 3.167}, "University CT": {"tournamentComp": 1.852, "fullNames": "James Cullers & Varun Tamaskar", "lastNames": ["Cullers", "Tamaskar"], "prelimRecord": [4, 2], "prelimRank": [16, 56], "breakRecord": [3, 1], "eliminated": [0, 0, "Semis", "Semifinals", "University YP"], "speaks": [{"name": "Cullers James", "rawAVG": 29.0, "adjAVG": 29.0}, {"name": "Tamaskar Varun", "rawAVG": 28.42, "adjAVG": 28.42}], "goldBid": false, "silverBid": true, "breakBoost": 5, "tournamentBoost": 1, "OPwpm": 3.333}, "University MN": {"tournamentComp": 1.167, "fullNames": "Ananth Menon & Marcus Novak", "lastNames": ["Menon", "Novak"], "prelimRecord": [4, 2], "prelimRank": [17, 56], "breakRecord": [1, 1], "eliminated": [0, 0, "Octafinals", "Octafinals", "University YP"], "speaks": [{"name": "Menon Ananth", "rawAVG": 28.75, "adjAVG": 29.3}, {"name": "Novak Marcus", "rawAVG": 28.92, "adjAVG": 29.5}], "goldBid": false, "silverBid": false, "breakBoost": 3, "tournamentBoost": 1, "OPwpm": 3.5}, "University YP": {"tournamentComp": 2.222, "fullNames": "Daniel Yan & Abraham Paik", "lastNames": ["Yan", "Paik"], "prelimRecord": [4, 2], "prelimRank": [18, 56], "breakRecord": [2, 3], "eliminated": [1, 2, "Finals", "Finals", "Bellaire RS"], "speaks": [{"name": "Yan Daniel", "rawAVG": 28.5, "adjAVG": 29.2}, {"name": "Paik Abraham", "rawAVG": 28.33, "adjAVG": 29.0}], "goldBid": true, "silverBid": false, "breakBoost": 6, "tournamentBoost": 1, "OPwpm": 3.333}, "Vestavia Hills BS": {"tournamentComp": 0.704, "fullNames": "Maya Bridgwaters & Alex Stern", "lastNames": ["Bridgwaters", "Stern"], "prelimRecord": [4, 2], "prelimRank": [19, 56], "breakRecord": [0, 1], "eliminated": [1, 2, "Double Octafinals", "Double Octafinals", "Altamont SG"], "speaks": [{"name": "Bridgwaters Maya", "rawAVG": 27.92, "adjAVG": 27.92}, {"name": "Stern Alex", "rawAVG": 28.0, "adjAVG": 28.0}], "goldBid": false, "silverBid": false, "breakBoost": 2, "tournamentBoost": 1, "OPwpm": 3.167}, "West Broward PL": {"tournamentComp": 0.556, "fullNames": "Hassan Palanpurwala & Ethan Lawrence", "lastNames": ["Palanpurwala", "Lawrence"], "prelimRecord": [4, 2], "prelimRank": [20, 56], "breakRecord": [0, 1], "eliminated": [0, 3, "Double Octafinals", "Double Octafinals", "University CT"], "speaks": [{"name": "Palanpurwala Hassan", "rawAVG": 28.33, "adjAVG": 28.33}, {"name": "Lawrence Ethan", "rawAVG": 27.75, "adjAVG": 27.75}], "goldBid": false, "silverBid": false, "breakBoost": 2, "tournamentBoost": 1, "OPwpm": 2.5}, "Albuquerque AL": {"tournamentComp": 0.25, "fullNames": "Noor Ali & Sophia Liem", "lastNames": ["Liem", "Ali"], "prelimRecord": [3, 3], "prelimRank": [21, 56], "breakRecord": null, "eliminated": "Prelims", "speaks": [{"name": "Ali Noor", "rawAVG": 28.08, "adjAVG": 28.7}, {"name": "Liem Sophia", "rawAVG": 27.67, "adjAVG": 28.2}], "goldBid": false, "silverBid": false, "breakBoost": 1, "tournamentBoost": 1, "OPwpm": 3.0}, "Albuquerque CC": {"tournamentComp": 0.25, "fullNames": "Aiden Cruz & Ethan Cruz", "lastNames": ["Cruz", "Cruz"], "prelimRecord": [3, 3], "prelimRank": [22, 56], "breakRecord": null, "eliminated": "Prelims", "speaks": [{"name": "Cruz Aiden", "rawAVG": 28.0, "adjAVG": 28.0}, {"name": "Cruz Ethan", "rawAVG": 28.0, "adjAVG": 28.0}], "goldBid": false, "silverBid": false, "breakBoost": 1, "tournamentBoost": 1, "OPwpm": 3.0}, "Albuquerque JW": {"tournamentComp": 0.319, "fullNames": "Ankit Jaiswal & Sofia Wolinski", "lastNames": ["Jaiswal", "Wolinski"], "prelimRecord": [3, 3], "prelimRank": [23, 56], "breakRecord": null, "eliminated": "Prelims", "speaks": [{"name": "Jaiswal Ankit", "rawAVG": 28.25, "adjAVG": 28.25}, {"name": "Wolinski Sofia", "rawAVG": 28.33, "adjAVG": 28.33}], "goldBid": false, "silverBid": false, "breakBoost": 1, "tournamentBoost": 1, "OPwpm": 3.833}, "Bergen County Academies NN": {"tournamentComp": 0.25, "fullNames": "Elaine Nam & Avital Nozic", "lastNames": ["Nozic", "Nam"], "prelimRecord": [3, 3], "prelimRank": [24, 56], "breakRecord": null, "eliminated": "Prelims", "speaks": [{"name": "Nam Elaine", "rawAVG": 28.8, "adjAVG": 28.8}, {"name": "Nozic Avital", "rawAVG": 28.6, "adjAVG": 28.88}], "goldBid": false, "silverBid": false, "breakBoost": 1, "tournamentBoost": 1, "OPwpm": 3.0}, "Brookline SM": {"tournamentComp": 0.319, "fullNames": "Olivia Sheehan & Valeriya Mesquita", "lastNames": ["Sheehan", "Mesquita"], "prelimRecord": [3, 3], "prelimRank": [25, 56], "breakRecord": null, "eliminated": "Prelims", "speaks": [{"name": "Sheehan Olivia", "rawAVG": 29.08, "adjAVG": 29.08}, {"name": "Mesquita Valeriya", "rawAVG": 29.25, "adjAVG": 29.25}], "goldBid": false, "silverBid": false, "breakBoost": 1, "tournamentBoost": 1, "OPwpm": 3.833}, "Crescenta Valley KH": {"tournamentComp": 0.264, "fullNames": "Ellena Kim & Eun Chan Hyung", "lastNames": ["Kim", "Hyung"], "prelimRecord": [3, 3], "prelimRank": [26, 56], "breakRecord": null, "eliminated": "Prelims", "speaks": [{"name": "Kim Ellena", "rawAVG": 28.25, "adjAVG": 28.25}, {"name": "Hyung Eun Chan", "rawAVG": 27.75, "adjAVG": 27.75}], "goldBid": false, "silverBid": false, "breakBoost": 1, "tournamentBoost": 1, "OPwpm": 3.167}, "Dublin Jerome AZ": {"tournamentComp": 0.278, "fullNames": "Rohan Athavale & Brian Zhou", "lastNames": ["Athavale", "Zhou"], "prelimRecord": [3, 3], "prelimRank": [27, 56], "breakRecord": null, "eliminated": "Prelims", "speaks": [{"name": "Athavale Rohan", "rawAVG": 27.92, "adjAVG": 27.92}, {"name": "Zhou Brian", "rawAVG": 27.92, "adjAVG": 27.92}], "goldBid": false, "silverBid": false, "breakBoost": 1, "tournamentBoost": 1, "OPwpm": 3.333}, "Durham SW": {"tournamentComp": 0.292, "fullNames": "Anirudh Sukhija & Teddy Wallen", "lastNames": ["Sukhija", "Wallen"], "prelimRecord": [3, 3], "prelimRank": [28, 56], "breakRecord": null, "eliminated": "Prelims", "speaks": [{"name": "Sukhija Anirudh", "rawAVG": 28.42, "adjAVG": 28.42}, {"name": "Wallen Teddy", "rawAVG": 29.08, "adjAVG": 29.0}], "goldBid": false, "silverBid": false, "breakBoost": 1, "tournamentBoost": 1, "OPwpm": 3.5}, "James River BM": {"tournamentComp": 0.25, "fullNames": "Ellie Bowman & Danielle Min", "lastNames": ["Bowman", "Min"], "prelimRecord": [3, 3], "prelimRank": [29, 56], "breakRecord": null, "eliminated": "Prelims", "speaks": [{"name": "Bowman Ellie", "rawAVG": 28.0, "adjAVG": 28.0}, {"name": "Min Danielle", "rawAVG": 27.75, "adjAVG": 27.75}], "goldBid": false, "silverBid": false, "breakBoost": 1, "tournamentBoost": 1, "OPwpm": 3.0}, "James River FM": {"tournamentComp": 0.233, "fullNames": "Kayleigh Floyd & Dylan McEntyre", "lastNames": ["Floyd", "McEntyre"], "prelimRecord": [3, 3], "prelimRank": [30, 56], "breakRecord": null, "eliminated": "Prelims", "speaks": [{"name": "Floyd Kayleigh", "rawAVG": 27.5, "adjAVG": 27.5}, {"name": "McEntyre Dylan", "rawAVG": 27.25, "adjAVG": 27.25}], "goldBid": false, "silverBid": false, "breakBoost": 1, "tournamentBoost": 1, "OPwpm": 2.8}, "Laurel Christian HP": {"tournamentComp": 0.208, "fullNames": "Fletcher Horne & John Pickering", "lastNames": ["Horne", "Pickering"], "prelimRecord": [3, 3], "prelimRank": [31, 56], "breakRecord": null, "eliminated": "Prelims", "speaks": [{"name": "Horne Fletcher", "rawAVG": 28.0, "adjAVG": 27.8}, {"name": "Pickering John", "rawAVG": 27.42, "adjAVG": 27.1}], "goldBid": false, "silverBid": false, "breakBoost": 1, "tournamentBoost": 1, "OPwpm": 2.5}, "Mississippi School For Mathematics & Science LW": {"tournamentComp": 0.347, "fullNames": "Michael Lu & Aaron Wan", "lastNames": ["Lu", "Wan"], "prelimRecord": [3, 3], "prelimRank": [32, 56], "breakRecord": null, "eliminated": "Prelims", "speaks": [{"name": "Lu Michael", "rawAVG": 28.5, "adjAVG": 28.5}, {"name": "Wan Aaron", "rawAVG": 28.75, "adjAVG": 28.75}], "goldBid": false, "silverBid": false, "breakBoost": 1, "tournamentBoost": 1, "OPwpm": 4.167}, "Mississippi School For Mathematics & Science NY": {"tournamentComp": 0.222, "fullNames": "Lyem Ningthou & Andrew Yu", "lastNames": ["Ningthou", "Yu"], "prelimRecord": [3, 3], "prelimRank": [33, 56], "breakRecord": null, "eliminated": "Prelims", "speaks": [{"name": "Ningthou Lyem", "rawAVG": 28.8, "adjAVG": 28.8}, {"name": "Yu Andrew", "rawAVG": 28.6, "adjAVG": 28.6}], "goldBid": false, "silverBid": false, "breakBoost": 1, "tournamentBoost": 1, "OPwpm": 2.667}, "New Century Tech DS": {"tournamentComp": 0.25, "fullNames": "Ella Duus & Django Sarow", "lastNames": ["Duus", "Sarow"], "prelimRecord": [3, 3], "prelimRank": [34, 56], "breakRecord": null, "eliminated": "Prelims", "speaks": [{"name": "Duus Ella", "rawAVG": 28.33, "adjAVG": 28.33}, {"name": "Sarow Django", "rawAVG": 27.58, "adjAVG": 27.58}], "goldBid": false, "silverBid": false, "breakBoost": 1, "tournamentBoost": 1, "OPwpm": 3.0}, "Pine View PM": {"tournamentComp": 0.208, "fullNames": "Madison Ponder & Zander Moricz", "lastNames": ["Ponder", "Moricz"], "prelimRecord": [3, 3], "prelimRank": [35, 56], "breakRecord": null, "eliminated": "Prelims", "speaks": [{"name": "Ponder Madison", "rawAVG": 28.08, "adjAVG": 28.08}, {"name": "Moricz Zander", "rawAVG": 28.17, "adjAVG": 28.17}], "goldBid": false, "silverBid": false, "breakBoost": 1, "tournamentBoost": 1, "OPwpm": 2.5}, "Ransom Everglades SA": {"tournamentComp": 0.292, "fullNames": "Oliver Segal & Daniel Amron", "lastNames": ["Segal", "Amron"], "prelimRecord": [3, 3], "prelimRank": [36, 56], "breakRecord": null, "eliminated": "Prelims", "speaks": [{"name": "Segal Oliver", "rawAVG": 28.33, "adjAVG": 28.33}, {"name": "Amron Daniel", "rawAVG": 28.5, "adjAVG": 28.5}], "goldBid": false, "silverBid": false, "breakBoost": 1, "tournamentBoost": 1, "OPwpm": 3.5}, "Redwood GJ": {"tournamentComp": 0.233, "fullNames": "Ashish Goswami & Leonardo Jia", "lastNames": ["Goswami", "Jia"], "prelimRecord": [3, 3], "prelimRank": [37, 56], "breakRecord": null, "eliminated": "Prelims", "speaks": [{"name": "Goswami Ashish", "rawAVG": 28.1, "adjAVG": 28.1}, {"name": "Jia Leonardo", "rawAVG": 28.3, "adjAVG": 28.88}], "goldBid": false, "silverBid": false, "breakBoost": 1, "tournamentBoost": 1, "OPwpm": 2.8}, "Altamont SZ": {"tournamentComp": 0.236, "fullNames": "Sophia Sultan & Iman Zuberi", "lastNames": ["Sultan", "Zuberi"], "prelimRecord": [3, 3], "prelimRank": [38, 56], "breakRecord": null, "eliminated": "Prelims", "speaks": [{"name": "Sultan Sophia", "rawAVG": 28.58, "adjAVG": 28.58}, {"name": "Zuberi Iman", "rawAVG": 28.42, "adjAVG": 28.42}], "goldBid": false, "silverBid": false, "breakBoost": 1, "tournamentBoost": 1, "OPwpm": 2.833}, "Baton Rouge AT": {"tournamentComp": 0.157, "fullNames": "Hannah Anderson & Lillian Thibaut", "lastNames": ["Anderson", "Thibaut"], "prelimRecord": [2, 4], "prelimRank": [39, 56], "breakRecord": null, "eliminated": "Prelims", "speaks": [{"name": "Anderson Hannah", "rawAVG": 28.33, "adjAVG": 28.33}, {"name": "Thibaut Lillian", "rawAVG": 28.25, "adjAVG": 28.25}], "goldBid": false, "silverBid": false, "breakBoost": 1, "tournamentBoost": 1, "OPwpm": 2.833}, "Brentwood PY": {"tournamentComp": 0.111, "fullNames": "Shiv Patel & Nitya Yelliah", "lastNames": ["Patel", "Yelliah"], "prelimRecord": [2, 4], "prelimRank": [40, 56], "breakRecord": null, "eliminated": "Prelims", "speaks": [{"name": "Patel Shiv", "rawAVG": 27.08, "adjAVG": 27.12}, {"name": "Yelliah Nitya", "rawAVG": 27.33, "adjAVG": 27.1}], "goldBid": false, "silverBid": false, "breakBoost": 1, "tournamentBoost": 1, "OPwpm": 2.0}, "La Cueva GuWa": {"tournamentComp": 0.157, "fullNames": "Harmony Guan & Emily Wang", "lastNames": ["Guan", "Wang"], "prelimRecord": [2, 4], "prelimRank": [41, 56], "breakRecord": null, "eliminated": "Prelims", "speaks": [{"name": "Guan Harmony", "rawAVG": 27.17, "adjAVG": 27.17}, {"name": "Wang Emily", "rawAVG": 26.42, "adjAVG": 26.42}], "goldBid": false, "silverBid": false, "breakBoost": 1, "tournamentBoost": 1, "OPwpm": 2.833}, "La Cueva GW": {"tournamentComp": 0.12, "fullNames": "Hunter Guan & Jane Wei", "lastNames": ["Guan", "Wei"], "prelimRecord": [2, 4], "prelimRank": [42, 56], "breakRecord": null, "eliminated": "Prelims", "speaks": [{"name": "Guan Hunter", "rawAVG": 27.67, "adjAVG": 27.67}, {"name": "Wei Jane", "rawAVG": 27.92, "adjAVG": 27.92}], "goldBid": false, "silverBid": false, "breakBoost": 1, "tournamentBoost": 1, "OPwpm": 2.167}, "La Cueva SM": {"tournamentComp": 0.111, "fullNames": "Aiden Shoppel & Venkata Menta", "lastNames": ["Shoppel", "Menta"], "prelimRecord": [2, 4], "prelimRank": [43, 56], "breakRecord": null, "eliminated": "Prelims", "speaks": [{"name": "Shoppel Aiden", "rawAVG": 27.17, "adjAVG": 27.17}, {"name": "Menta Venkata", "rawAVG": 26.08, "adjAVG": 26.08}], "goldBid": false, "silverBid": false, "breakBoost": 1, "tournamentBoost": 1, "OPwpm": 2.0}, "Maggie L Walker Governor's BM": {"tournamentComp": 0.12, "fullNames": "Ria Bakshi & Shreya Malani", "lastNames": ["Bakshey", "Malani"], "prelimRecord": [2, 4], "prelimRank": [44, 56], "breakRecord": null, "eliminated": "Prelims", "speaks": [{"name": "Bakshi Ria", "rawAVG": 27.92, "adjAVG": 27.92}, {"name": "Malani Shreya", "rawAVG": 28.0, "adjAVG": 28.3}], "goldBid": false, "silverBid": false, "breakBoost": 1, "tournamentBoost": 1, "OPwpm": 2.167}, "Maggie L Walker Governor's FG": {"tournamentComp": 0.157, "fullNames": "Vena Flournoy & Jamilah Ganyuma", "lastNames": ["Flournoy", "Ganyuma"], "prelimRecord": [2, 4], "prelimRank": [45, 56], "breakRecord": null, "eliminated": "Prelims", "speaks": [{"name": "Flournoy Vena", "rawAVG": 28.17, "adjAVG": 28.4}, {"name": "Ganyuma Jamilah", "rawAVG": 28.08, "adjAVG": 28.08}], "goldBid": false, "silverBid": false, "breakBoost": 1, "tournamentBoost": 1, "OPwpm": 2.833}, "Maggie L Walker Governor's TR": {"tournamentComp": 0.156, "fullNames": "Sarah Townshend & Diya Ram Mohan", "lastNames": ["Townshend", "RamMohan"], "prelimRecord": [2, 4], "prelimRank": [46, 56], "breakRecord": null, "eliminated": "Prelims", "speaks": [{"name": "Townshend Sarah", "rawAVG": 27.6, "adjAVG": 27.5}, {"name": "Ram Mohan Diya", "rawAVG": 27.8, "adjAVG": 27.8}], "goldBid": false, "silverBid": false, "breakBoost": 1, "tournamentBoost": 1, "OPwpm": 2.8}, "Ransom Everglades KF": {"tournamentComp": 0.157, "fullNames": "Veronica Kerr & Amelia Fox", "lastNames": ["Kerr", "Fox"], "prelimRecord": [2, 4], "prelimRank": [47, 56], "breakRecord": null, "eliminated": "Prelims", "speaks": [{"name": "Kerr Veronica", "rawAVG": 28.5, "adjAVG": 28.5}, {"name": "Fox Amelia", "rawAVG": 28.42, "adjAVG": 28.42}], "goldBid": false, "silverBid": false, "breakBoost": 1, "tournamentBoost": 1, "OPwpm": 2.833}, "Ransom Everglades MZ": {"tournamentComp": 0.156, "fullNames": "Jackson McAliley & Marco Zhao", "lastNames": ["McAliley", "Zhao"], "prelimRecord": [2, 4], "prelimRank": [48, 56], "breakRecord": null, "eliminated": "Prelims", "speaks": [{"name": "McAliley Jackson", "rawAVG": 27.67, "adjAVG": 27.67}, {"name": "Zhao Marco", "rawAVG": 27.42, "adjAVG": 27.42}], "goldBid": false, "silverBid": false, "breakBoost": 1, "tournamentBoost": 1, "OPwpm": 2.8}, "St Andrew's Episcopal CN": {"tournamentComp": 0.157, "fullNames": "Abhirup Chatterjee & Yahya Naveed", "lastNames": ["Chatterjee", "Naveed"], "prelimRecord": [2, 4], "prelimRank": [49, 56], "breakRecord": null, "eliminated": "Prelims", "speaks": [{"name": "Chatterjee Abhirup", "rawAVG": 28.83, "adjAVG": 28.83}, {"name": "Naveed Yahya", "rawAVG": 28.42, "adjAVG": 28.42}], "goldBid": false, "silverBid": false, "breakBoost": 1, "tournamentBoost": 1, "OPwpm": 2.833}, "University Pro BZ": {"tournamentComp": 0.12, "fullNames": "Elda Berhaneyessus & Adrielle Zindler", "lastNames": ["Zindler", "Berhaneyessus"], "prelimRecord": [2, 4], "prelimRank": [50, 56], "breakRecord": null, "eliminated": "Prelims", "speaks": [{"name": "Berhaneyessus Elda", "rawAVG": 28.25, "adjAVG": 28.0}, {"name": "Zindler Adrielle", "rawAVG": 28.25, "adjAVG": 28.25}], "goldBid": false, "silverBid": false, "breakBoost": 1, "tournamentBoost": 1, "OPwpm": 2.167}, "Vestavia Hills AV": {"tournamentComp": 0.167, "fullNames": "Aarya Aluri & Amith Varambally", "lastNames": ["Aluri", "Varambally"], "prelimRecord": [2, 4], "prelimRank": [51, 56], "breakRecord": null, "eliminated": "Prelims", "speaks": [{"name": "Aluri Aarya", "rawAVG": 27.67, "adjAVG": 27.67}, {"name": "Varambally Amith", "rawAVG": 28.0, "adjAVG": 28.0}], "goldBid": false, "silverBid": false, "breakBoost": 1, "tournamentBoost": 1, "OPwpm": 3.0}, "Brentwood SV": {"tournamentComp": 0.065, "fullNames": "Sanjana Sitaram & Ananya Varshney", "lastNames": ["Sitaram", "Varshney"], "prelimRecord": [1, 5], "prelimRank": [52, 56], "breakRecord": null, "eliminated": "Prelims", "speaks": [{"name": "Sitaram Sanjana", "rawAVG": 27.92, "adjAVG": 27.88}, {"name": "Varshney Ananya", "rawAVG": 27.83, "adjAVG": 27.6}], "goldBid": false, "silverBid": false, "breakBoost": 1, "tournamentBoost": 1, "OPwpm": 2.333}, "Livingston HF": {"tournamentComp": 0.06, "fullNames": "Jonathan Hong & Tyler Ferreira", "lastNames": ["Hong", "Ferreira"], "prelimRecord": [1, 5], "prelimRank": [53, 56], "breakRecord": null, "eliminated": "Prelims", "speaks": [{"name": "Hong Jonathan", "rawAVG": 27.67, "adjAVG": 27.67}, {"name": "Ferreira Tyler", "rawAVG": 27.25, "adjAVG": 27.25}], "goldBid": false, "silverBid": false, "breakBoost": 1, "tournamentBoost": 1, "OPwpm": 2.167}, "Baton Rouge FS": {"tournamentComp": 0.0, "fullNames": "Jane Foreman & Maven Skillman", "lastNames": ["Foreman", "Skillman"], "prelimRecord": [0, 6], "prelimRank": [54, 56], "breakRecord": null, "eliminated": "Prelims", "speaks": [{"name": "Foreman Jane", "rawAVG": 28.08, "adjAVG": 28.4}, {"name": "Skillman Maven", "rawAVG": 27.83, "adjAVG": 27.83}], "goldBid": false, "silverBid": false, "breakBoost": 1, "tournamentBoost": 1, "OPwpm": 2.833}, "Baton Rouge MM": {"tournamentComp": 0.0, "fullNames": "Andrew Meche & Sean Murphy", "lastNames": ["Meche", "Murphy"], "prelimRecord": [0, 6], "prelimRank": [55, 56], "breakRecord": null, "eliminated": "Prelims", "speaks": [{"name": "Meche Andrew", "rawAVG": 27.2, "adjAVG": 27.0}, {"name": "Murphy Sean", "rawAVG": 27.1, "adjAVG": 26.62}], "goldBid": false, "silverBid": false, "breakBoost": 1, "tournamentBoost": 1, "OPwpm": 2.667}, "Baton Rouge PW": {"tournamentComp": 0.0, "fullNames": "Holly Phan & Brianna Watkins", "lastNames": ["Phan", "Watkins"], "prelimRecord": [0, 6], "prelimRank": [56, 56], "breakRecord": null, "eliminated": "Prelims", "speaks": [{"name": "Phan Holly", "rawAVG": 27.75, "adjAVG": 27.75}, {"name": "Watkins Brianna", "rawAVG": 27.17, "adjAVG": 27.4}], "goldBid": false, "silverBid": false, "breakBoost": 1, "tournamentBoost": 1, "OPwpm": 2.333}}}