{
    "AZ 6053": {
        "rounds": [
            {
                "round": "Round 5",
                "win": true,
                "side": "CON",
                "opp": "AF 6028",
                "decision": [
                    2,
                    0
                ]
            },
            {
                "round": "Round 4",
                "win": true,
                "side": "PRO",
                "opp": "AH 6001",
                "decision": [
                    2,
                    0
                ]
            },
            {
                "round": "Round 3",
                "win": true,
                "side": "CON",
                "opp": "AT 6021",
                "decision": [
                    2,
                    0
                ]
            },
            {
                "round": "Round 2",
                "win": true,
                "side": "CON",
                "opp": "CF 6055",
                "decision": [
                    2,
                    0
                ]
            },
            {
                "round": "Round 1",
                "win": true,
                "side": "PRO",
                "opp": "AL 6012",
                "decision": [
                    2,
                    0
                ]
            },
            {
                "round": "Semis",
                "win": false,
                "side": "PRO",
                "opp": "AF 6027",
                "decision": [
                    1,
                    2
                ]
            },
            {
                "round": "Qtrs",
                "win": true,
                "side": "CON",
                "opp": "AK 6009",
                "decision": [
                    3,
                    0
                ]
            },
            {
                "round": "Octos",
                "win": true,
                "side": "PRO",
                "opp": "BD 6040",
                "decision": [
                    3,
                    0
                ]
            }
        ],
        "names": [
            "Soares Giselle",
            "Kohli Binti"
        ]
    },
    "AK 6008": {
        "rounds": [
            {
                "round": "Round 5",
                "win": true,
                "side": "CON",
                "opp": "AH 6001",
                "decision": [
                    2,
                    0
                ]
            },
            {
                "round": "Round 4",
                "win": null,
                "side": "CON",
                "opp": "AF 6027",
                "decision": [
                    1,
                    1
                ]
            },
            {
                "round": "Round 3",
                "win": true,
                "side": "CON",
                "opp": "AT 6022",
                "decision": [
                    2,
                    0
                ]
            },
            {
                "round": "Round 2",
                "win": true,
                "side": "PRO",
                "opp": "AP 6041",
                "decision": [
                    2,
                    0
                ]
            },
            {
                "round": "Round 1",
                "win": true,
                "side": "PRO",
                "opp": "CF 6054",
                "decision": [
                    2,
                    0
                ]
            },
            {
                "round": "Finals",
                "win": true,
                "side": "PRO",
                "opp": "AF 6027",
                "decision": [
                    4,
                    1
                ]
            },
            {
                "round": "Semis",
                "win": true,
                "side": "PRO",
                "opp": "AZ 6052",
                "decision": [
                    3,
                    0
                ]
            },
            {
                "round": "Qtrs",
                "win": true,
                "side": "PRO",
                "opp": "AF 6030",
                "decision": [
                    3,
                    0
                ]
            },
            {
                "round": "Octos",
                "win": true,
                "side": "CON",
                "opp": "CM 6061",
                "decision": [
                    3,
                    0
                ]
            }
        ],
        "names": [
            "Giesecke Johnathon",
            "Cochran Burke"
        ]
    },
    "AZ 6052": {
        "rounds": [
            {
                "round": "Round 5",
                "win": true,
                "side": "CON",
                "opp": "BD 6037",
                "decision": [
                    2,
                    0
                ]
            },
            {
                "round": "Round 4",
                "win": true,
                "side": "PRO",
                "opp": "BS 6047",
                "decision": [
                    2,
                    0
                ]
            },
            {
                "round": "Round 3",
                "win": null,
                "side": "CON",
                "opp": "AT 6023",
                "decision": [
                    1,
                    1
                ]
            },
            {
                "round": "Round 2",
                "win": true,
                "side": "PRO",
                "opp": "AM 6016",
                "decision": [
                    2,
                    0
                ]
            },
            {
                "round": "Round 1",
                "win": true,
                "side": "CON",
                "opp": "AH 6003",
                "decision": [
                    2,
                    0
                ]
            },
            {
                "round": "Semis",
                "win": false,
                "side": "CON",
                "opp": "AK 6008",
                "decision": [
                    0,
                    3
                ]
            },
            {
                "round": "Qtrs",
                "win": true,
                "side": "PRO",
                "opp": "AT 6023",
                "decision": [
                    2,
                    1
                ]
            },
            {
                "round": "Octos",
                "win": true,
                "side": "CON",
                "opp": "BD 6039",
                "decision": [
                    2,
                    1
                ]
            }
        ],
        "names": [
            "Gansukh Baigalmaa",
            "Desetty Viraj"
        ]
    },
    "AF 6028": {
        "rounds": [
            {
                "round": "Round 5",
                "win": false,
                "side": "PRO",
                "opp": "AZ 6053",
                "decision": [
                    0,
                    2
                ]
            },
            {
                "round": "Round 4",
                "win": true,
                "side": "CON",
                "opp": "AL 6013",
                "decision": [
                    2,
                    0
                ]
            },
            {
                "round": "Round 3",
                "win": true,
                "side": "CON",
                "opp": "AP 6017",
                "decision": [
                    2,
                    0
                ]
            },
            {
                "round": "Round 2",
                "win": true,
                "side": "CON",
                "opp": "CC 6048",
                "decision": [
                    2,
                    0
                ]
            },
            {
                "round": "Round 1",
                "win": true,
                "side": "CON",
                "opp": "AJ 6005",
                "decision": [
                    2,
                    0
                ]
            },
            {
                "round": "Qtrs",
                "win": null,
                "side": "PRO",
                "opp": "AF 6027",
                "decision": [
                    0,
                    0
                ]
            },
            {
                "round": "Octos",
                "win": true,
                "side": "CON",
                "opp": "BD 6037",
                "decision": [
                    3,
                    0
                ]
            }
        ],
        "names": [
            "Bhatia Mayank",
            "Kim Matthew"
        ]
    },
    "AT 6020": {
        "rounds": [
            {
                "round": "Round 5",
                "win": true,
                "side": "CON",
                "opp": "AL 6013",
                "decision": [
                    2,
                    0
                ]
            },
            {
                "round": "Round 4",
                "win": null,
                "side": "CON",
                "opp": "AC 6026",
                "decision": [
                    1,
                    1
                ]
            },
            {
                "round": "Round 3",
                "win": null,
                "side": "CON",
                "opp": "AF 6030",
                "decision": [
                    1,
                    1
                ]
            },
            {
                "round": "Round 2",
                "win": true,
                "side": "PRO",
                "opp": "AM 6015",
                "decision": [
                    2,
                    0
                ]
            },
            {
                "round": "Round 1",
                "win": true,
                "side": "PRO",
                "opp": "CC 6014",
                "decision": [
                    2,
                    0
                ]
            },
            {
                "round": "Octos",
                "win": false,
                "side": "PRO",
                "opp": "AF 6030",
                "decision": [
                    0,
                    3
                ]
            }
        ],
        "names": [
            "Martiniak Kyle",
            "Han Simon"
        ]
    },
    "AT 6023": {
        "rounds": [
            {
                "round": "Round 5",
                "win": null,
                "side": "PRO",
                "opp": "AF 6029",
                "decision": [
                    1,
                    1
                ]
            },
            {
                "round": "Round 4",
                "win": true,
                "side": "PRO",
                "opp": "AH 6003",
                "decision": [
                    2,
                    0
                ]
            },
            {
                "round": "Round 3",
                "win": null,
                "side": "PRO",
                "opp": "AZ 6052",
                "decision": [
                    1,
                    1
                ]
            },
            {
                "round": "Round 2",
                "win": true,
                "side": "PRO",
                "opp": "AK 6011",
                "decision": [
                    2,
                    0
                ]
            },
            {
                "round": "Round 1",
                "win": true,
                "side": "PRO",
                "opp": "AP 6041",
                "decision": [
                    2,
                    0
                ]
            },
            {
                "round": "Qtrs",
                "win": false,
                "side": "CON",
                "opp": "AZ 6052",
                "decision": [
                    1,
                    2
                ]
            },
            {
                "round": "Octos",
                "win": true,
                "side": "CON",
                "opp": "AT 6021",
                "decision": [
                    3,
                    0
                ]
            }
        ],
        "names": [
            "Granato Victoria",
            "Kenes Eric"
        ]
    },
    "AF 6027": {
        "rounds": [
            {
                "round": "Round 5",
                "win": null,
                "side": "CON",
                "opp": "AT 6021",
                "decision": [
                    1,
                    1
                ]
            },
            {
                "round": "Round 4",
                "win": null,
                "side": "PRO",
                "opp": "AK 6008",
                "decision": [
                    1,
                    1
                ]
            },
            {
                "round": "Round 3",
                "win": true,
                "side": "PRO",
                "opp": "BS 6047",
                "decision": [
                    2,
                    0
                ]
            },
            {
                "round": "Round 2",
                "win": true,
                "side": "PRO",
                "opp": "BH 6042",
                "decision": [
                    2,
                    0
                ]
            },
            {
                "round": "Round 1",
                "win": true,
                "side": "CON",
                "opp": "CN 6059",
                "decision": [
                    2,
                    0
                ]
            },
            {
                "round": "Finals",
                "win": false,
                "side": "CON",
                "opp": "AK 6008",
                "decision": [
                    1,
                    4
                ]
            },
            {
                "round": "Semis",
                "win": true,
                "side": "CON",
                "opp": "AZ 6053",
                "decision": [
                    2,
                    1
                ]
            },
            {
                "round": "Qtrs",
                "win": null,
                "side": "CON",
                "opp": "AF 6028",
                "decision": [
                    0,
                    0
                ]
            },
            {
                "round": "Octos",
                "win": true,
                "side": "CON",
                "opp": "AJ 6006",
                "decision": [
                    2,
                    1
                ]
            }
        ],
        "names": [
            "Murakami Michael",
            "Gao Bill"
        ]
    },
    "AF 6029": {
        "rounds": [
            {
                "round": "Round 5",
                "win": null,
                "side": "CON",
                "opp": "AT 6023",
                "decision": [
                    1,
                    1
                ]
            },
            {
                "round": "Round 4",
                "win": true,
                "side": "PRO",
                "opp": "CM 6060",
                "decision": [
                    2,
                    0
                ]
            },
            {
                "round": "Round 3",
                "win": true,
                "side": "PRO",
                "opp": "AC 6000",
                "decision": [
                    2,
                    0
                ]
            },
            {
                "round": "Round 2",
                "win": null,
                "side": "CON",
                "opp": "BD 6039",
                "decision": [
                    1,
                    1
                ]
            },
            {
                "round": "Round 1",
                "win": true,
                "side": "PRO",
                "opp": "AH 6036",
                "decision": [
                    2,
                    0
                ]
            },
            {
                "round": "Octos",
                "win": false,
                "side": "CON",
                "opp": "AK 6009",
                "decision": [
                    1,
                    2
                ]
            }
        ],
        "names": [
            "Sriram Nikhil",
            "Wu Sharon"
        ]
    },
    "AK 6009": {
        "rounds": [
            {
                "round": "Round 5",
                "win": true,
                "side": "PRO",
                "opp": "AC 6024",
                "decision": [
                    2,
                    0
                ]
            },
            {
                "round": "Round 4",
                "win": true,
                "side": "PRO",
                "opp": "CG 6056",
                "decision": [
                    2,
                    0
                ]
            },
            {
                "round": "Round 3",
                "win": null,
                "side": "PRO",
                "opp": "BL 6032",
                "decision": [
                    1,
                    1
                ]
            },
            {
                "round": "Round 2",
                "win": false,
                "side": "PRO",
                "opp": "AH 6001",
                "decision": [
                    0,
                    2
                ]
            },
            {
                "round": "Round 1",
                "win": true,
                "side": "PRO",
                "opp": "CC 6049",
                "decision": [
                    2,
                    0
                ]
            },
            {
                "round": "Qtrs",
                "win": false,
                "side": "PRO",
                "opp": "AZ 6053",
                "decision": [
                    0,
                    3
                ]
            },
            {
                "round": "Octos",
                "win": true,
                "side": "PRO",
                "opp": "AF 6029",
                "decision": [
                    2,
                    1
                ]
            }
        ],
        "names": [
            "Shelton Lauren",
            "Milles Michael"
        ]
    },
    "BD 6037": {
        "rounds": [
            {
                "round": "Round 5",
                "win": false,
                "side": "PRO",
                "opp": "AZ 6052",
                "decision": [
                    0,
                    2
                ]
            },
            {
                "round": "Round 4",
                "win": true,
                "side": "PRO",
                "opp": "AT 6022",
                "decision": [
                    2,
                    0
                ]
            },
            {
                "round": "Round 3",
                "win": true,
                "side": "CON",
                "opp": "CC 6058",
                "decision": [
                    2,
                    0
                ]
            },
            {
                "round": "Round 2",
                "win": null,
                "side": "PRO",
                "opp": "AJ 6006",
                "decision": [
                    1,
                    1
                ]
            },
            {
                "round": "Round 1",
                "win": true,
                "side": "PRO",
                "opp": "AP 6018",
                "decision": [
                    2,
                    0
                ]
            },
            {
                "round": "Octos",
                "win": false,
                "side": "PRO",
                "opp": "AF 6028",
                "decision": [
                    0,
                    3
                ]
            }
        ],
        "names": [
            "Daudi Shamoun",
            "Qazi Aleena"
        ]
    },
    "AF 6030": {
        "rounds": [
            {
                "round": "Round 5",
                "win": true,
                "side": "CON",
                "opp": "BD 6038",
                "decision": [
                    2,
                    0
                ]
            },
            {
                "round": "Round 4",
                "win": false,
                "side": "CON",
                "opp": "AT 6021",
                "decision": [
                    0,
                    2
                ]
            },
            {
                "round": "Round 3",
                "win": null,
                "side": "PRO",
                "opp": "AT 6020",
                "decision": [
                    1,
                    1
                ]
            },
            {
                "round": "Round 2",
                "win": true,
                "side": "CON",
                "opp": "BL 6032",
                "decision": [
                    2,
                    0
                ]
            },
            {
                "round": "Round 1",
                "win": true,
                "side": "CON",
                "opp": "AK 6010",
                "decision": [
                    2,
                    0
                ]
            },
            {
                "round": "Qtrs",
                "win": false,
                "side": "CON",
                "opp": "AK 6008",
                "decision": [
                    0,
                    3
                ]
            },
            {
                "round": "Octos",
                "win": true,
                "side": "CON",
                "opp": "AT 6020",
                "decision": [
                    3,
                    0
                ]
            }
        ],
        "names": [
            "Mercado Miguel",
            "Kim Andrew"
        ]
    },
    "AH 6001": {
        "rounds": [
            {
                "round": "Round 5",
                "win": false,
                "side": "PRO",
                "opp": "AK 6008",
                "decision": [
                    0,
                    2
                ]
            },
            {
                "round": "Round 4",
                "win": false,
                "side": "CON",
                "opp": "AZ 6053",
                "decision": [
                    0,
                    2
                ]
            },
            {
                "round": "Round 3",
                "win": true,
                "side": "CON",
                "opp": "AC 6026",
                "decision": [
                    2,
                    0
                ]
            },
            {
                "round": "Round 2",
                "win": true,
                "side": "CON",
                "opp": "AK 6009",
                "decision": [
                    2,
                    0
                ]
            },
            {
                "round": "Round 1",
                "win": true,
                "side": "PRO",
                "opp": "AM 6015",
                "decision": [
                    2,
                    0
                ]
            }
        ],
        "names": [
            "Livingston Tyler",
            "Taxali Shaurya"
        ]
    },
    "AH 6003": {
        "rounds": [
            {
                "round": "Round 5",
                "win": true,
                "side": "PRO",
                "opp": "BL 6044",
                "decision": [
                    2,
                    0
                ]
            },
            {
                "round": "Round 4",
                "win": false,
                "side": "CON",
                "opp": "AT 6023",
                "decision": [
                    0,
                    2
                ]
            },
            {
                "round": "Round 3",
                "win": true,
                "side": "CON",
                "opp": "CG 6056",
                "decision": [
                    2,
                    0
                ]
            },
            {
                "round": "Round 2",
                "win": true,
                "side": "PRO",
                "opp": "AC 6000",
                "decision": [
                    2,
                    0
                ]
            },
            {
                "round": "Round 1",
                "win": false,
                "side": "PRO",
                "opp": "AZ 6052",
                "decision": [
                    0,
                    2
                ]
            }
        ],
        "names": [
            "Han James",
            "Shin Yvin"
        ]
    },
    "AT 6021": {
        "rounds": [
            {
                "round": "Round 5",
                "win": null,
                "side": "PRO",
                "opp": "AF 6027",
                "decision": [
                    1,
                    1
                ]
            },
            {
                "round": "Round 4",
                "win": true,
                "side": "PRO",
                "opp": "AF 6030",
                "decision": [
                    2,
                    0
                ]
            },
            {
                "round": "Round 3",
                "win": false,
                "side": "PRO",
                "opp": "AZ 6053",
                "decision": [
                    0,
                    2
                ]
            },
            {
                "round": "Round 2",
                "win": true,
                "side": "PRO",
                "opp": "BD 6038",
                "decision": [
                    2,
                    0
                ]
            },
            {
                "round": "Round 1",
                "win": true,
                "side": "BYE",
                "opp": null,
                "decision": null
            },
            {
                "round": "Octos",
                "win": false,
                "side": "PRO",
                "opp": "AT 6023",
                "decision": [
                    0,
                    3
                ]
            }
        ],
        "names": [
            "Kovacevic Maya",
            "Kenes Lizzy"
        ]
    },
    "AJ 6006": {
        "rounds": [
            {
                "round": "Round 5",
                "win": null,
                "side": "CON",
                "opp": "AT 6022",
                "decision": [
                    1,
                    1
                ]
            },
            {
                "round": "Round 4",
                "win": true,
                "side": "CON",
                "opp": "AC 6000",
                "decision": [
                    2,
                    0
                ]
            },
            {
                "round": "Round 3",
                "win": null,
                "side": "CON",
                "opp": "CM 6062",
                "decision": [
                    1,
                    1
                ]
            },
            {
                "round": "Round 2",
                "win": null,
                "side": "CON",
                "opp": "BD 6037",
                "decision": [
                    1,
                    1
                ]
            },
            {
                "round": "Round 1",
                "win": true,
                "side": "PRO",
                "opp": "AL 6013",
                "decision": [
                    2,
                    0
                ]
            },
            {
                "round": "Octos",
                "win": false,
                "side": "PRO",
                "opp": "AF 6027",
                "decision": [
                    1,
                    2
                ]
            }
        ],
        "names": [
            "Choudhry Amal",
            "Amra Sireen"
        ]
    },
    "CM 6061": {
        "rounds": [
            {
                "round": "Round 5",
                "win": null,
                "side": "PRO",
                "opp": "BS 6047",
                "decision": [
                    1,
                    1
                ]
            },
            {
                "round": "Round 4",
                "win": true,
                "side": "CON",
                "opp": "CC 6058",
                "decision": [
                    2,
                    0
                ]
            },
            {
                "round": "Round 3",
                "win": null,
                "side": "PRO",
                "opp": "AJ 6007",
                "decision": [
                    1,
                    1
                ]
            },
            {
                "round": "Round 2",
                "win": true,
                "side": "PRO",
                "opp": "BL 6043",
                "decision": [
                    2,
                    0
                ]
            },
            {
                "round": "Round 1",
                "win": null,
                "side": "PRO",
                "opp": "BD 6038",
                "decision": [
                    1,
                    1
                ]
            },
            {
                "round": "Octos",
                "win": false,
                "side": "PRO",
                "opp": "AK 6008",
                "decision": [
                    0,
                    3
                ]
            }
        ],
        "names": [
            "Basu Nikita",
            "Zhang Liz"
        ]
    },
    "BD 6039": {
        "rounds": [
            {
                "round": "Round 5",
                "win": null,
                "side": "PRO",
                "opp": "CM 6060",
                "decision": [
                    1,
                    1
                ]
            },
            {
                "round": "Round 4",
                "win": true,
                "side": "PRO",
                "opp": "AH 6036",
                "decision": [
                    2,
                    0
                ]
            },
            {
                "round": "Round 3",
                "win": true,
                "side": "PRO",
                "opp": "BH 6042",
                "decision": [
                    2,
                    0
                ]
            },
            {
                "round": "Round 2",
                "win": null,
                "side": "PRO",
                "opp": "AF 6029",
                "decision": [
                    1,
                    1
                ]
            },
            {
                "round": "Round 1",
                "win": null,
                "side": "PRO",
                "opp": "AK 6011",
                "decision": [
                    1,
                    1
                ]
            },
            {
                "round": "Octos",
                "win": false,
                "side": "PRO",
                "opp": "AZ 6052",
                "decision": [
                    1,
                    2
                ]
            }
        ],
        "names": [
            "Lopez Valery",
            "Kalle Rahul"
        ]
    },
    "AJ 6007": {
        "rounds": [
            {
                "round": "Round 5",
                "win": null,
                "side": "CON",
                "opp": "AC 6026",
                "decision": [
                    1,
                    1
                ]
            },
            {
                "round": "Round 4",
                "win": true,
                "side": "CON",
                "opp": "BL 6043",
                "decision": [
                    2,
                    0
                ]
            },
            {
                "round": "Round 3",
                "win": null,
                "side": "CON",
                "opp": "CM 6061",
                "decision": [
                    1,
                    1
                ]
            },
            {
                "round": "Round 2",
                "win": true,
                "side": "CON",
                "opp": "AH 6002",
                "decision": [
                    2,
                    0
                ]
            },
            {
                "round": "Round 1",
                "win": false,
                "side": "CON",
                "opp": "AT 6022",
                "decision": [
                    0,
                    2
                ]
            }
        ],
        "names": [
            "Fry Georgia",
            "Solis Estefany"
        ]
    },
    "AC 6026": {
        "rounds": [
            {
                "round": "Round 5",
                "win": null,
                "side": "PRO",
                "opp": "AJ 6007",
                "decision": [
                    1,
                    1
                ]
            },
            {
                "round": "Round 4",
                "win": null,
                "side": "PRO",
                "opp": "AT 6020",
                "decision": [
                    1,
                    1
                ]
            },
            {
                "round": "Round 3",
                "win": false,
                "side": "PRO",
                "opp": "AH 6001",
                "decision": [
                    0,
                    2
                ]
            },
            {
                "round": "Round 2",
                "win": true,
                "side": "CON",
                "opp": "AJ 6004",
                "decision": [
                    2,
                    0
                ]
            },
            {
                "round": "Round 1",
                "win": true,
                "side": "CON",
                "opp": "CM 6062",
                "decision": [
                    2,
                    0
                ]
            }
        ],
        "names": [
            "Jejurikar Ajay",
            "Razi Amaan"
        ]
    },
    "CM 6062": {
        "rounds": [
            {
                "round": "Round 5",
                "win": null,
                "side": "PRO",
                "opp": "AL 6012",
                "decision": [
                    1,
                    1
                ]
            },
            {
                "round": "Round 4",
                "win": true,
                "side": "PRO",
                "opp": "AK 6011",
                "decision": [
                    2,
                    0
                ]
            },
            {
                "round": "Round 3",
                "win": null,
                "side": "PRO",
                "opp": "AJ 6006",
                "decision": [
                    1,
                    1
                ]
            },
            {
                "round": "Round 2",
                "win": true,
                "side": "CON",
                "opp": "AJ 6005",
                "decision": [
                    2,
                    0
                ]
            },
            {
                "round": "Round 1",
                "win": false,
                "side": "PRO",
                "opp": "AC 6026",
                "decision": [
                    0,
                    2
                ]
            }
        ],
        "names": [
            "Maddulapalli Anjali",
            "Krishnan Nivedha"
        ]
    },
    "BL 6032": {
        "rounds": [
            {
                "round": "Round 5",
                "win": true,
                "side": "PRO",
                "opp": "BH 6042",
                "decision": [
                    2,
                    0
                ]
            },
            {
                "round": "Round 4",
                "win": null,
                "side": "PRO",
                "opp": "AM 6016",
                "decision": [
                    1,
                    1
                ]
            },
            {
                "round": "Round 3",
                "win": null,
                "side": "CON",
                "opp": "AK 6009",
                "decision": [
                    1,
                    1
                ]
            },
            {
                "round": "Round 2",
                "win": false,
                "side": "PRO",
                "opp": "AF 6030",
                "decision": [
                    0,
                    2
                ]
            },
            {
                "round": "Round 1",
                "win": true,
                "side": "PRO",
                "opp": "AC 6025",
                "decision": [
                    2,
                    0
                ]
            }
        ],
        "names": [
            "Gauvin Olivia",
            "Hong Brian"
        ]
    },
    "BL 6044": {
        "rounds": [
            {
                "round": "Round 5",
                "win": false,
                "side": "CON",
                "opp": "AH 6003",
                "decision": [
                    0,
                    2
                ]
            },
            {
                "round": "Round 4",
                "win": true,
                "side": "CON",
                "opp": "CF 6055",
                "decision": [
                    2,
                    0
                ]
            },
            {
                "round": "Round 3",
                "win": null,
                "side": "PRO",
                "opp": "AM 6016",
                "decision": [
                    1,
                    1
                ]
            },
            {
                "round": "Round 2",
                "win": true,
                "side": "CON",
                "opp": "CF 6054",
                "decision": [
                    2,
                    0
                ]
            },
            {
                "round": "Round 1",
                "win": null,
                "side": "CON",
                "opp": "CG 6057",
                "decision": [
                    1,
                    1
                ]
            }
        ],
        "names": [
            "Li Jessica",
            "Corliss Catharine"
        ]
    },
    "AL 6012": {
        "rounds": [
            {
                "round": "Round 5",
                "win": null,
                "side": "CON",
                "opp": "CM 6062",
                "decision": [
                    1,
                    1
                ]
            },
            {
                "round": "Round 4",
                "win": true,
                "side": "CON",
                "opp": "CG 6057",
                "decision": [
                    2,
                    0
                ]
            },
            {
                "round": "Round 3",
                "win": true,
                "side": "CON",
                "opp": "AH 6002",
                "decision": [
                    2,
                    0
                ]
            },
            {
                "round": "Round 2",
                "win": null,
                "side": "CON",
                "opp": "AP 6018",
                "decision": [
                    1,
                    1
                ]
            },
            {
                "round": "Round 1",
                "win": false,
                "side": "CON",
                "opp": "AZ 6053",
                "decision": [
                    0,
                    2
                ]
            }
        ],
        "names": [
            "Gajewski Remy",
            "Sidime Mariama"
        ]
    },
    "BD 6040": {
        "rounds": [
            {
                "round": "Round 5",
                "win": true,
                "side": "CON",
                "opp": "CF 6055",
                "decision": [
                    2,
                    0
                ]
            },
            {
                "round": "Round 4",
                "win": null,
                "side": "PRO",
                "opp": "AM 6015",
                "decision": [
                    1,
                    1
                ]
            },
            {
                "round": "Round 3",
                "win": null,
                "side": "CON",
                "opp": "AC 6024",
                "decision": [
                    1,
                    1
                ]
            },
            {
                "round": "Round 2",
                "win": false,
                "side": "PRO",
                "opp": "CM 6060",
                "decision": [
                    0,
                    2
                ]
            },
            {
                "round": "Round 1",
                "win": true,
                "side": "CON",
                "opp": "CC 6048",
                "decision": [
                    2,
                    0
                ]
            },
            {
                "round": "Octos",
                "win": false,
                "side": "CON",
                "opp": "AZ 6053",
                "decision": [
                    0,
                    3
                ]
            }
        ],
        "names": [
            "Herod Max",
            "Pillai Pranav"
        ]
    },
    "AM 6016": {
        "rounds": [
            {
                "round": "Round 5",
                "win": true,
                "side": "CON",
                "opp": "CC 6058",
                "decision": [
                    2,
                    0
                ]
            },
            {
                "round": "Round 4",
                "win": null,
                "side": "CON",
                "opp": "BL 6032",
                "decision": [
                    1,
                    1
                ]
            },
            {
                "round": "Round 3",
                "win": null,
                "side": "CON",
                "opp": "BL 6044",
                "decision": [
                    1,
                    1
                ]
            },
            {
                "round": "Round 2",
                "win": false,
                "side": "CON",
                "opp": "AZ 6052",
                "decision": [
                    0,
                    2
                ]
            },
            {
                "round": "Round 1",
                "win": true,
                "side": "CON",
                "opp": "AH 6002",
                "decision": [
                    2,
                    0
                ]
            }
        ],
        "names": [
            "Cohen Oliver",
            "Maher Brigid"
        ]
    },
    "AT 6022": {
        "rounds": [
            {
                "round": "Round 5",
                "win": null,
                "side": "PRO",
                "opp": "AJ 6006",
                "decision": [
                    1,
                    1
                ]
            },
            {
                "round": "Round 4",
                "win": false,
                "side": "CON",
                "opp": "BD 6037",
                "decision": [
                    0,
                    2
                ]
            },
            {
                "round": "Round 3",
                "win": false,
                "side": "PRO",
                "opp": "AK 6008",
                "decision": [
                    0,
                    2
                ]
            },
            {
                "round": "Round 2",
                "win": true,
                "side": "PRO",
                "opp": "CC 6049",
                "decision": [
                    2,
                    0
                ]
            },
            {
                "round": "Round 1",
                "win": true,
                "side": "PRO",
                "opp": "AJ 6007",
                "decision": [
                    2,
                    0
                ]
            }
        ],
        "names": [
            "Walsh Kaitlin",
            "Schwartz John"
        ]
    },
    "AC 6024": {
        "rounds": [
            {
                "round": "Round 5",
                "win": false,
                "side": "CON",
                "opp": "AK 6009",
                "decision": [
                    0,
                    2
                ]
            },
            {
                "round": "Round 4",
                "win": true,
                "side": "PRO",
                "opp": "AP 6018",
                "decision": [
                    2,
                    0
                ]
            },
            {
                "round": "Round 3",
                "win": null,
                "side": "PRO",
                "opp": "BD 6040",
                "decision": [
                    1,
                    1
                ]
            },
            {
                "round": "Round 2",
                "win": false,
                "side": "PRO",
                "opp": "BS 6047",
                "decision": [
                    0,
                    2
                ]
            },
            {
                "round": "Round 1",
                "win": true,
                "side": "PRO",
                "opp": "BH 6042",
                "decision": [
                    2,
                    0
                ]
            }
        ],
        "names": [
            "Castellon Cole",
            "Brownell Nate"
        ]
    },
    "CG 6057": {
        "rounds": [
            {
                "round": "Round 5",
                "win": true,
                "side": "PRO",
                "opp": "CC 6049",
                "decision": [
                    2,
                    0
                ]
            },
            {
                "round": "Round 4",
                "win": false,
                "side": "PRO",
                "opp": "AL 6012",
                "decision": [
                    0,
                    2
                ]
            },
            {
                "round": "Round 3",
                "win": false,
                "side": "PRO",
                "opp": "AL 6013",
                "decision": [
                    0,
                    2
                ]
            },
            {
                "round": "Round 2",
                "win": true,
                "side": "PRO",
                "opp": "CC 6014",
                "decision": [
                    2,
                    0
                ]
            },
            {
                "round": "Round 1",
                "win": null,
                "side": "PRO",
                "opp": "BL 6044",
                "decision": [
                    1,
                    1
                ]
            }
        ],
        "names": [
            "Thumu Manasvi",
            "Gupta Shrutika"
        ]
    },
    "CM 6060": {
        "rounds": [
            {
                "round": "Round 5",
                "win": null,
                "side": "CON",
                "opp": "BD 6039",
                "decision": [
                    1,
                    1
                ]
            },
            {
                "round": "Round 4",
                "win": false,
                "side": "CON",
                "opp": "AF 6029",
                "decision": [
                    0,
                    2
                ]
            },
            {
                "round": "Round 3",
                "win": true,
                "side": "CON",
                "opp": "AH 6036",
                "decision": [
                    2,
                    0
                ]
            },
            {
                "round": "Round 2",
                "win": true,
                "side": "CON",
                "opp": "BD 6040",
                "decision": [
                    2,
                    0
                ]
            },
            {
                "round": "Round 1",
                "win": null,
                "side": "PRO",
                "opp": "AT 6021",
                "decision": [
                    0,
                    0
                ]
            }
        ],
        "names": [
            "Gudur Anish",
            "Kweon Daniel"
        ]
    },
    "BS 6047": {
        "rounds": [
            {
                "round": "Round 5",
                "win": null,
                "side": "CON",
                "opp": "CM 6061",
                "decision": [
                    1,
                    1
                ]
            },
            {
                "round": "Round 4",
                "win": false,
                "side": "CON",
                "opp": "AZ 6052",
                "decision": [
                    0,
                    2
                ]
            },
            {
                "round": "Round 3",
                "win": false,
                "side": "CON",
                "opp": "AF 6027",
                "decision": [
                    0,
                    2
                ]
            },
            {
                "round": "Round 2",
                "win": true,
                "side": "CON",
                "opp": "AC 6024",
                "decision": [
                    2,
                    0
                ]
            },
            {
                "round": "Round 1",
                "win": true,
                "side": "PRO",
                "opp": "CC 6058",
                "decision": [
                    2,
                    0
                ]
            }
        ],
        "names": [
            "Bozkurt Arman",
            "Orhon Lara"
        ]
    },
    "BD 6038": {
        "rounds": [
            {
                "round": "Round 5",
                "win": false,
                "side": "PRO",
                "opp": "AF 6030",
                "decision": [
                    0,
                    2
                ]
            },
            {
                "round": "Round 4",
                "win": true,
                "side": "CON",
                "opp": "AP 6017",
                "decision": [
                    2,
                    0
                ]
            },
            {
                "round": "Round 3",
                "win": true,
                "side": "PRO",
                "opp": "CF 6054",
                "decision": [
                    2,
                    0
                ]
            },
            {
                "round": "Round 2",
                "win": false,
                "side": "CON",
                "opp": "AT 6021",
                "decision": [
                    0,
                    2
                ]
            },
            {
                "round": "Round 1",
                "win": null,
                "side": "CON",
                "opp": "CM 6061",
                "decision": [
                    1,
                    1
                ]
            }
        ],
        "names": [
            "Satish Shruti",
            "Anandan Dheepa"
        ]
    },
    "AJ 6005": {
        "rounds": [
            {
                "round": "Round 5",
                "win": true,
                "side": "PRO",
                "opp": "CF 6046",
                "decision": [
                    2,
                    0
                ]
            },
            {
                "round": "Round 4",
                "win": true,
                "side": "PRO",
                "opp": "CN 6059",
                "decision": [
                    2,
                    0
                ]
            },
            {
                "round": "Round 3",
                "win": false,
                "side": "PRO",
                "opp": "AM 6015",
                "decision": [
                    0,
                    2
                ]
            },
            {
                "round": "Round 2",
                "win": false,
                "side": "PRO",
                "opp": "CM 6062",
                "decision": [
                    0,
                    2
                ]
            },
            {
                "round": "Round 1",
                "win": false,
                "side": "PRO",
                "opp": "AF 6028",
                "decision": [
                    0,
                    2
                ]
            }
        ],
        "names": [
            "Mansour Linda",
            "Sowa Jakub"
        ]
    },
    "AC 6000": {
        "rounds": [
            {
                "round": "Round 5",
                "win": true,
                "side": "PRO",
                "opp": "AJ 6004",
                "decision": [
                    2,
                    0
                ]
            },
            {
                "round": "Round 4",
                "win": false,
                "side": "PRO",
                "opp": "AJ 6006",
                "decision": [
                    0,
                    2
                ]
            },
            {
                "round": "Round 3",
                "win": false,
                "side": "CON",
                "opp": "AF 6029",
                "decision": [
                    0,
                    2
                ]
            },
            {
                "round": "Round 2",
                "win": false,
                "side": "CON",
                "opp": "AH 6003",
                "decision": [
                    0,
                    2
                ]
            },
            {
                "round": "Round 1",
                "win": true,
                "side": "CON",
                "opp": "CF 6055",
                "decision": [
                    2,
                    0
                ]
            }
        ],
        "names": [
            "Kumar Anchal",
            "Mryan Noor"
        ]
    },
    "AL 6013": {
        "rounds": [
            {
                "round": "Round 5",
                "win": false,
                "side": "PRO",
                "opp": "AT 6020",
                "decision": [
                    0,
                    2
                ]
            },
            {
                "round": "Round 4",
                "win": false,
                "side": "PRO",
                "opp": "AF 6028",
                "decision": [
                    0,
                    2
                ]
            },
            {
                "round": "Round 3",
                "win": true,
                "side": "CON",
                "opp": "CG 6057",
                "decision": [
                    2,
                    0
                ]
            },
            {
                "round": "Round 2",
                "win": true,
                "side": "CON",
                "opp": "CN 6059",
                "decision": [
                    2,
                    0
                ]
            },
            {
                "round": "Round 1",
                "win": false,
                "side": "CON",
                "opp": "AJ 6006",
                "decision": [
                    0,
                    2
                ]
            }
        ],
        "names": [
            "McKinney Harper",
            "Carson Dylan"
        ]
    },
    "AH 6036": {
        "rounds": [
            {
                "round": "Round 5",
                "win": true,
                "side": "CON",
                "opp": "AK 6010",
                "decision": [
                    2,
                    0
                ]
            },
            {
                "round": "Round 4",
                "win": false,
                "side": "CON",
                "opp": "BD 6039",
                "decision": [
                    0,
                    2
                ]
            },
            {
                "round": "Round 3",
                "win": false,
                "side": "PRO",
                "opp": "CM 6060",
                "decision": [
                    0,
                    2
                ]
            },
            {
                "round": "Round 2",
                "win": true,
                "side": "CON",
                "opp": "CF 6046",
                "decision": [
                    2,
                    0
                ]
            },
            {
                "round": "Round 1",
                "win": false,
                "side": "CON",
                "opp": "AF 6029",
                "decision": [
                    0,
                    2
                ]
            }
        ],
        "names": [
            "Kim David",
            "Park Irene"
        ]
    },
    "AK 6010": {
        "rounds": [
            {
                "round": "Round 5",
                "win": false,
                "side": "PRO",
                "opp": "AH 6036",
                "decision": [
                    0,
                    2
                ]
            },
            {
                "round": "Round 4",
                "win": true,
                "side": "PRO",
                "opp": "CF 6054",
                "decision": [
                    2,
                    0
                ]
            },
            {
                "round": "Round 3",
                "win": null,
                "side": "PRO",
                "opp": "CC 6049",
                "decision": [
                    1,
                    1
                ]
            },
            {
                "round": "Round 2",
                "win": null,
                "side": "CON",
                "opp": "CG 6056",
                "decision": [
                    1,
                    1
                ]
            },
            {
                "round": "Round 1",
                "win": false,
                "side": "PRO",
                "opp": "AF 6030",
                "decision": [
                    0,
                    2
                ]
            }
        ],
        "names": [
            "Worthy Hailey",
            "Torbert Liam"
        ]
    },
    "AK 6011": {
        "rounds": [
            {
                "round": "Round 5",
                "win": null,
                "side": "CON",
                "opp": "AP 6018",
                "decision": [
                    1,
                    1
                ]
            },
            {
                "round": "Round 4",
                "win": false,
                "side": "CON",
                "opp": "CM 6062",
                "decision": [
                    0,
                    2
                ]
            },
            {
                "round": "Round 3",
                "win": true,
                "side": "PRO",
                "opp": "CC 6014",
                "decision": [
                    2,
                    0
                ]
            },
            {
                "round": "Round 2",
                "win": false,
                "side": "CON",
                "opp": "AT 6023",
                "decision": [
                    0,
                    2
                ]
            },
            {
                "round": "Round 1",
                "win": null,
                "side": "CON",
                "opp": "BD 6039",
                "decision": [
                    1,
                    1
                ]
            }
        ],
        "names": [
            "Parker Mara",
            "Major McKenna"
        ]
    },
    "CF 6046": {
        "rounds": [
            {
                "round": "Round 5",
                "win": false,
                "side": "CON",
                "opp": "AJ 6005",
                "decision": [
                    0,
                    2
                ]
            },
            {
                "round": "Round 4",
                "win": true,
                "side": "CON",
                "opp": "CC 6048",
                "decision": [
                    2,
                    0
                ]
            },
            {
                "round": "Round 3",
                "win": null,
                "side": "PRO",
                "opp": "AC 6025",
                "decision": [
                    1,
                    1
                ]
            },
            {
                "round": "Round 2",
                "win": false,
                "side": "PRO",
                "opp": "AH 6036",
                "decision": [
                    0,
                    2
                ]
            },
            {
                "round": "Round 1",
                "win": null,
                "side": "PRO",
                "opp": "AP 6017",
                "decision": [
                    1,
                    1
                ]
            }
        ],
        "names": [
            "Hwang Sunny",
            "Wellisch Benji"
        ]
    },
    "AC 6025": {
        "rounds": [
            {
                "round": "Round 5",
                "win": true,
                "side": "CON",
                "opp": "CC 6048",
                "decision": [
                    2,
                    0
                ]
            },
            {
                "round": "Round 4",
                "win": null,
                "side": "CON",
                "opp": "AH 6002",
                "decision": [
                    1,
                    1
                ]
            },
            {
                "round": "Round 3",
                "win": null,
                "side": "CON",
                "opp": "CF 6046",
                "decision": [
                    1,
                    1
                ]
            },
            {
                "round": "Round 2",
                "win": false,
                "side": "CON",
                "opp": "AP 6017",
                "decision": [
                    0,
                    2
                ]
            },
            {
                "round": "Round 1",
                "win": false,
                "side": "CON",
                "opp": "BL 6032",
                "decision": [
                    0,
                    2
                ]
            }
        ],
        "names": [
            "Singhal Ayushi",
            "Parkins Katie"
        ]
    },
    "AP 6017": {
        "rounds": [
            {
                "round": "Round 5",
                "win": null,
                "side": "CON",
                "opp": "CG 6056",
                "decision": [
                    1,
                    1
                ]
            },
            {
                "round": "Round 4",
                "win": false,
                "side": "PRO",
                "opp": "BD 6038",
                "decision": [
                    0,
                    2
                ]
            },
            {
                "round": "Round 3",
                "win": false,
                "side": "PRO",
                "opp": "AF 6028",
                "decision": [
                    0,
                    2
                ]
            },
            {
                "round": "Round 2",
                "win": true,
                "side": "PRO",
                "opp": "AC 6025",
                "decision": [
                    2,
                    0
                ]
            },
            {
                "round": "Round 1",
                "win": null,
                "side": "CON",
                "opp": "CF 6046",
                "decision": [
                    1,
                    1
                ]
            }
        ],
        "names": [
            "McKillip Audrey",
            "Nash Taylor"
        ]
    },
    "AP 6018": {
        "rounds": [
            {
                "round": "Round 5",
                "win": null,
                "side": "PRO",
                "opp": "AK 6011",
                "decision": [
                    1,
                    1
                ]
            },
            {
                "round": "Round 4",
                "win": false,
                "side": "CON",
                "opp": "AC 6024",
                "decision": [
                    0,
                    2
                ]
            },
            {
                "round": "Round 3",
                "win": true,
                "side": "CON",
                "opp": "CC 6048",
                "decision": [
                    2,
                    0
                ]
            },
            {
                "round": "Round 2",
                "win": null,
                "side": "PRO",
                "opp": "AL 6012",
                "decision": [
                    1,
                    1
                ]
            },
            {
                "round": "Round 1",
                "win": false,
                "side": "CON",
                "opp": "BD 6037",
                "decision": [
                    0,
                    2
                ]
            }
        ],
        "names": [
            "Austin Deja",
            "Vann Levale"
        ]
    },
    "BL 6043": {
        "rounds": [
            {
                "round": "Round 5",
                "win": null,
                "side": "PRO",
                "opp": "AM 6015",
                "decision": [
                    1,
                    1
                ]
            },
            {
                "round": "Round 4",
                "win": false,
                "side": "PRO",
                "opp": "AJ 6007",
                "decision": [
                    0,
                    2
                ]
            },
            {
                "round": "Round 3",
                "win": true,
                "side": "PRO",
                "opp": "AP 6041",
                "decision": [
                    2,
                    0
                ]
            },
            {
                "round": "Round 2",
                "win": false,
                "side": "CON",
                "opp": "CM 6061",
                "decision": [
                    0,
                    2
                ]
            },
            {
                "round": "Round 1",
                "win": null,
                "side": "PRO",
                "opp": "AJ 6004",
                "decision": [
                    1,
                    1
                ]
            }
        ],
        "names": [
            "Sekili Jason",
            "Konshin Karina"
        ]
    },
    "AM 6015": {
        "rounds": [
            {
                "round": "Round 5",
                "win": null,
                "side": "CON",
                "opp": "BL 6043",
                "decision": [
                    1,
                    1
                ]
            },
            {
                "round": "Round 4",
                "win": null,
                "side": "CON",
                "opp": "BD 6040",
                "decision": [
                    1,
                    1
                ]
            },
            {
                "round": "Round 3",
                "win": true,
                "side": "CON",
                "opp": "AJ 6005",
                "decision": [
                    2,
                    0
                ]
            },
            {
                "round": "Round 2",
                "win": false,
                "side": "CON",
                "opp": "AT 6020",
                "decision": [
                    0,
                    2
                ]
            },
            {
                "round": "Round 1",
                "win": false,
                "side": "CON",
                "opp": "AH 6001",
                "decision": [
                    0,
                    2
                ]
            }
        ],
        "names": [
            "Oskandy Nicolas",
            "Cohen Julian"
        ]
    },
    "CC 6049": {
        "rounds": [
            {
                "round": "Round 5",
                "win": false,
                "side": "CON",
                "opp": "CG 6057",
                "decision": [
                    0,
                    2
                ]
            },
            {
                "round": "Round 4",
                "win": true,
                "side": "CON",
                "opp": "AP 6041",
                "decision": [
                    2,
                    0
                ]
            },
            {
                "round": "Round 3",
                "win": null,
                "side": "CON",
                "opp": "AK 6010",
                "decision": [
                    1,
                    1
                ]
            },
            {
                "round": "Round 2",
                "win": false,
                "side": "CON",
                "opp": "AT 6022",
                "decision": [
                    0,
                    2
                ]
            },
            {
                "round": "Round 1",
                "win": false,
                "side": "CON",
                "opp": "AK 6009",
                "decision": [
                    0,
                    2
                ]
            }
        ],
        "names": [
            "Civantos Joseph",
            "Kadri Danish"
        ]
    },
    "CG 6056": {
        "rounds": [
            {
                "round": "Round 5",
                "win": null,
                "side": "PRO",
                "opp": "AP 6017",
                "decision": [
                    1,
                    1
                ]
            },
            {
                "round": "Round 4",
                "win": false,
                "side": "CON",
                "opp": "AK 6009",
                "decision": [
                    0,
                    2
                ]
            },
            {
                "round": "Round 3",
                "win": false,
                "side": "PRO",
                "opp": "AH 6003",
                "decision": [
                    0,
                    2
                ]
            },
            {
                "round": "Round 2",
                "win": null,
                "side": "PRO",
                "opp": "AK 6010",
                "decision": [
                    1,
                    1
                ]
            },
            {
                "round": "Round 1",
                "win": true,
                "side": "BYE",
                "opp": null,
                "decision": null
            }
        ],
        "names": [
            "Singh Vidhi",
            "Baffoe Peter"
        ]
    },
    "CF 6054": {
        "rounds": [
            {
                "round": "Round 5",
                "win": true,
                "side": "BYE",
                "opp": null,
                "decision": null
            },
            {
                "round": "Round 4",
                "win": false,
                "side": "CON",
                "opp": "AK 6010",
                "decision": [
                    0,
                    2
                ]
            },
            {
                "round": "Round 3",
                "win": false,
                "side": "CON",
                "opp": "BD 6038",
                "decision": [
                    0,
                    2
                ]
            },
            {
                "round": "Round 2",
                "win": false,
                "side": "PRO",
                "opp": "BL 6044",
                "decision": [
                    0,
                    2
                ]
            },
            {
                "round": "Round 1",
                "win": false,
                "side": "CON",
                "opp": "AK 6008",
                "decision": [
                    0,
                    2
                ]
            }
        ],
        "names": [
            "Hong Joseph",
            "Chumbley Sophia"
        ]
    },
    "CF 6055": {
        "rounds": [
            {
                "round": "Round 5",
                "win": false,
                "side": "PRO",
                "opp": "BD 6040",
                "decision": [
                    0,
                    2
                ]
            },
            {
                "round": "Round 4",
                "win": false,
                "side": "PRO",
                "opp": "BL 6044",
                "decision": [
                    0,
                    2
                ]
            },
            {
                "round": "Round 3",
                "win": true,
                "side": "BYE",
                "opp": null,
                "decision": null
            },
            {
                "round": "Round 2",
                "win": false,
                "side": "PRO",
                "opp": "AZ 6053",
                "decision": [
                    0,
                    2
                ]
            },
            {
                "round": "Round 1",
                "win": false,
                "side": "PRO",
                "opp": "AC 6000",
                "decision": [
                    0,
                    2
                ]
            }
        ],
        "names": [
            "Benbow Kyle",
            "Eisner Corey"
        ]
    },
    "BH 6042": {
        "rounds": [
            {
                "round": "Round 5",
                "win": false,
                "side": "CON",
                "opp": "BL 6032",
                "decision": [
                    0,
                    2
                ]
            },
            {
                "round": "Round 4",
                "win": true,
                "side": "BYE",
                "opp": null,
                "decision": null
            },
            {
                "round": "Round 3",
                "win": false,
                "side": "CON",
                "opp": "BD 6039",
                "decision": [
                    0,
                    2
                ]
            },
            {
                "round": "Round 2",
                "win": false,
                "side": "CON",
                "opp": "AF 6027",
                "decision": [
                    0,
                    2
                ]
            },
            {
                "round": "Round 1",
                "win": false,
                "side": "CON",
                "opp": "AC 6024",
                "decision": [
                    0,
                    2
                ]
            }
        ],
        "names": [
            "Krueger Kaitlyn",
            "Rada Connor"
        ]
    },
    "CC 6058": {
        "rounds": [
            {
                "round": "Round 5",
                "win": false,
                "side": "PRO",
                "opp": "AM 6016",
                "decision": [
                    0,
                    2
                ]
            },
            {
                "round": "Round 4",
                "win": false,
                "side": "PRO",
                "opp": "CM 6061",
                "decision": [
                    0,
                    2
                ]
            },
            {
                "round": "Round 3",
                "win": false,
                "side": "PRO",
                "opp": "BD 6037",
                "decision": [
                    0,
                    2
                ]
            },
            {
                "round": "Round 2",
                "win": true,
                "side": "BYE",
                "opp": null,
                "decision": null
            },
            {
                "round": "Round 1",
                "win": false,
                "side": "CON",
                "opp": "BS 6047",
                "decision": [
                    0,
                    2
                ]
            }
        ],
        "names": [
            "Fediv Ivan",
            "Doroba Alex"
        ]
    },
    "AJ 6004": {
        "rounds": [
            {
                "round": "Round 5",
                "win": false,
                "side": "CON",
                "opp": "AC 6000",
                "decision": [
                    0,
                    2
                ]
            },
            {
                "round": "Round 4",
                "win": null,
                "side": "PRO",
                "opp": "CC 6014",
                "decision": [
                    1,
                    1
                ]
            },
            {
                "round": "Round 3",
                "win": null,
                "side": "CON",
                "opp": "CN 6059",
                "decision": [
                    1,
                    1
                ]
            },
            {
                "round": "Round 2",
                "win": false,
                "side": "PRO",
                "opp": "AC 6026",
                "decision": [
                    0,
                    2
                ]
            },
            {
                "round": "Round 1",
                "win": null,
                "side": "CON",
                "opp": "BL 6043",
                "decision": [
                    1,
                    1
                ]
            }
        ],
        "names": [
            "Serna Mariela",
            "Meza Tahis"
        ]
    },
    "CC 6014": {
        "rounds": [
            {
                "round": "Round 5",
                "win": null,
                "side": "CON",
                "opp": "CN 6059",
                "decision": [
                    1,
                    1
                ]
            },
            {
                "round": "Round 4",
                "win": null,
                "side": "CON",
                "opp": "AJ 6004",
                "decision": [
                    1,
                    1
                ]
            },
            {
                "round": "Round 3",
                "win": false,
                "side": "CON",
                "opp": "AK 6011",
                "decision": [
                    0,
                    2
                ]
            },
            {
                "round": "Round 2",
                "win": false,
                "side": "CON",
                "opp": "CG 6057",
                "decision": [
                    0,
                    2
                ]
            },
            {
                "round": "Round 1",
                "win": false,
                "side": "CON",
                "opp": "AT 6020",
                "decision": [
                    0,
                    2
                ]
            }
        ],
        "names": [
            "Svanascini Frank",
            "Amato Mike"
        ]
    },
    "CN 6059": {
        "rounds": [
            {
                "round": "Round 5",
                "win": null,
                "side": "PRO",
                "opp": "CC 6014",
                "decision": [
                    1,
                    1
                ]
            },
            {
                "round": "Round 4",
                "win": false,
                "side": "CON",
                "opp": "AJ 6005",
                "decision": [
                    0,
                    2
                ]
            },
            {
                "round": "Round 3",
                "win": null,
                "side": "PRO",
                "opp": "AJ 6004",
                "decision": [
                    1,
                    1
                ]
            },
            {
                "round": "Round 2",
                "win": false,
                "side": "PRO",
                "opp": "AL 6013",
                "decision": [
                    0,
                    2
                ]
            },
            {
                "round": "Round 1",
                "win": false,
                "side": "PRO",
                "opp": "AF 6027",
                "decision": [
                    0,
                    2
                ]
            }
        ],
        "names": [
            "Kelley Ben",
            "Helm Meredith"
        ]
    },
    "AH 6002": {
        "rounds": [
            {
                "round": "Round 5",
                "win": null,
                "side": "PRO",
                "opp": "AP 6041",
                "decision": [
                    1,
                    1
                ]
            },
            {
                "round": "Round 4",
                "win": null,
                "side": "PRO",
                "opp": "AC 6025",
                "decision": [
                    1,
                    1
                ]
            },
            {
                "round": "Round 3",
                "win": false,
                "side": "PRO",
                "opp": "AL 6012",
                "decision": [
                    0,
                    2
                ]
            },
            {
                "round": "Round 2",
                "win": false,
                "side": "PRO",
                "opp": "AJ 6007",
                "decision": [
                    0,
                    2
                ]
            },
            {
                "round": "Round 1",
                "win": false,
                "side": "PRO",
                "opp": "AM 6016",
                "decision": [
                    0,
                    2
                ]
            }
        ],
        "names": [
            "Munn IV John",
            "Shim Joseph"
        ]
    },
    "AP 6041": {
        "rounds": [
            {
                "round": "Round 5",
                "win": null,
                "side": "CON",
                "opp": "AH 6002",
                "decision": [
                    1,
                    1
                ]
            },
            {
                "round": "Round 4",
                "win": false,
                "side": "PRO",
                "opp": "CC 6049",
                "decision": [
                    0,
                    2
                ]
            },
            {
                "round": "Round 3",
                "win": false,
                "side": "CON",
                "opp": "BL 6043",
                "decision": [
                    0,
                    2
                ]
            },
            {
                "round": "Round 2",
                "win": false,
                "side": "CON",
                "opp": "AK 6008",
                "decision": [
                    0,
                    2
                ]
            },
            {
                "round": "Round 1",
                "win": false,
                "side": "CON",
                "opp": "AT 6023",
                "decision": [
                    0,
                    2
                ]
            }
        ],
        "names": [
            "Parks Sinniyah",
            "Spencer Brooklyn"
        ]
    },
    "CC 6048": {
        "rounds": [
            {
                "round": "Round 5",
                "win": false,
                "side": "PRO",
                "opp": "AC 6025",
                "decision": [
                    0,
                    2
                ]
            },
            {
                "round": "Round 4",
                "win": false,
                "side": "PRO",
                "opp": "CF 6046",
                "decision": [
                    0,
                    2
                ]
            },
            {
                "round": "Round 3",
                "win": false,
                "side": "PRO",
                "opp": "AP 6018",
                "decision": [
                    0,
                    2
                ]
            },
            {
                "round": "Round 2",
                "win": false,
                "side": "PRO",
                "opp": "AF 6028",
                "decision": [
                    0,
                    2
                ]
            },
            {
                "round": "Round 1",
                "win": false,
                "side": "PRO",
                "opp": "BD 6040",
                "decision": [
                    0,
                    2
                ]
            }
        ],
        "names": [
            "Athey Thomas",
            "Fletcher Paul"
        ]
    }
}